grandcypher/__init__.py
grandcypher/test_hints.py
grandcypher/test_parser.py
grandcypher/test_queries.py
grand_cypher-1.0.1.dist-info/METADATA
grand_cypher-1.0.1.dist-info/WHEEL
grand_cypher-1.0.1.dist-info/licenses/LICENSE
grand_cypher-1.0.1.dist-info/RECORD
