Metadata-Version: 2.4
Name: grand-cypher
Version: 1.0.1
Summary: Query Grand and NetworkX graphs using Cypher syntax.
Author-email: Jordan Matelsky <opensource@matelsky.com>
License-File: LICENSE
Requires-Python: >=3.10
Requires-Dist: grandiso>=2.2.0
Requires-Dist: lark>=1.2.2
Requires-Dist: networkx>=3.4.2
